src/swingft_cli/__init__.py
src/swingft_cli/cli.py
src/swingft_cli/config.py
src/swingft_cli/utils.py
src/swingft_cli/validator.py
src/swingft_cli/BuildScript/build.sh
src/swingft_cli/BuildScript/build_project_yml.py
src/swingft_cli/BuildScript/complement.py
src/swingft_cli/BuildScript/main.py
src/swingft_cli/BuildScript/parser_pbxproj.py
src/swingft_cli/BuildScript/parser_structure.py
src/swingft_cli/BuildScript/parser_xcscheme.py
src/swingft_cli/Obfuscation_Pipeline/find_project.py
src/swingft_cli/Obfuscation_Pipeline/obf_pipeline.py
src/swingft_cli/Obfuscation_Pipeline/remove_debug_symbol.py
src/swingft_cli/Obfuscation_Pipeline/remove_files.py
src/swingft_cli/Obfuscation_Pipeline/swift_comment_remover.py
src/swingft_cli/Obfuscation_Pipeline/AST/__init__.py
src/swingft_cli/Obfuscation_Pipeline/AST/run_ast.py
src/swingft_cli/Obfuscation_Pipeline/AST/run_swift_syntax.py
src/swingft_cli/Obfuscation_Pipeline/AST/SyntaxAST/Package.resolved
src/swingft_cli/Obfuscation_Pipeline/AST/SyntaxAST/Package.swift
src/swingft_cli/Obfuscation_Pipeline/AST/SyntaxAST/Sources/main.swift
src/swingft_cli/Obfuscation_Pipeline/AST/SyntaxAST/Sources/Handler/ASTProcessor.swift
src/swingft_cli/Obfuscation_Pipeline/AST/SyntaxAST/Sources/Handler/ExternalHandler.swift
src/swingft_cli/Obfuscation_Pipeline/AST/SyntaxAST/Sources/Handler/InternalHandler.swift
src/swingft_cli/Obfuscation_Pipeline/AST/SyntaxAST/Sources/Handler/LocationHandler.swift
src/swingft_cli/Obfuscation_Pipeline/AST/SyntaxAST/Sources/Handler/NodeVisitor.swift
src/swingft_cli/Obfuscation_Pipeline/AST/SyntaxAST/Sources/InfoExtractor/ActorInfoExtractor.swift
src/swingft_cli/Obfuscation_Pipeline/AST/SyntaxAST/Sources/InfoExtractor/ClassInfoExtractor.swift
src/swingft_cli/Obfuscation_Pipeline/AST/SyntaxAST/Sources/InfoExtractor/EnumInfoExtractor.swift
src/swingft_cli/Obfuscation_Pipeline/AST/SyntaxAST/Sources/InfoExtractor/ExtensionInfoExtractor.swift
swingft-1.1.0.dist-info/METADATA
swingft-1.1.0.dist-info/WHEEL
swingft-1.1.0.dist-info/entry_points.txt
swingft-1.1.0.dist-info/top_level.txt
swingft-1.1.0.dist-info/RECORD
